[
  {
    "type": "constructor",
    "inputs": [
      {
        "name": "_prizePoolParams",
        "type": "tuple",
        "internalType": "struct PrizePoolParams",
        "components": [
          {
            "name": "owner",
            "type": "address",
            "internalType": "address"
          },
          {
            "name": "vault",
            "type": "address",
            "internalType": "address"
          },
          {
            "name": "feeRecipient",
            "type": "address",
            "internalType": "address"
          },
          {
            "name": "treasury",
            "type": "address",
            "internalType": "address"
          },
          {
            "name": "bonusConfig",
            "type": "tuple",
            "internalType": "struct BonusConfig",
            "components": [
              {
                "name": "bonusPerEpoch",
                "type": "uint256",
                "internalType": "uint256"
              },
              {
                "name": "maxBonus",
                "type": "uint256",
                "internalType": "uint256"
              },
              {
                "name": "decayPerEpoch",
                "type": "uint256",
                "internalType": "uint256"
              }
            ]
          },
          {
            "name": "epochConfig",
            "type": "tuple",
            "internalType": "struct EpochConfig",
            "components": [
              {
                "name": "epochDuration",
                "type": "uint256",
                "internalType": "uint256"
              },
              {
                "name": "entryDeadline",
                "type": "uint256",
                "internalType": "uint256"
              },
              {
                "name": "maxParticipants",
                "type": "uint256",
                "internalType": "uint256"
              }
            ]
          },
          {
            "name": "participationRules",
            "type": "tuple",
            "internalType": "struct ParticipationRules",
            "components": [
              {
                "name": "minDepositAmount",
                "type": "uint256",
                "internalType": "uint256"
              },
              {
                "name": "maxWithdrawFee",
                "type": "uint256",
                "internalType": "uint256"
              }
            ]
          }
        ]
      }
    ],
    "stateMutability": "nonpayable"
  },
  {
    "type": "function",
    "name": "FEE_DENOMINATOR",
    "inputs": [],
    "outputs": [
      {
        "name": "",
        "type": "uint256",
        "internalType": "uint256"
      }
    ],
    "stateMutability": "view"
  },
  {
    "type": "function",
    "name": "calculateWithdrawalFee",
    "inputs": [
      {
        "name": "amount",
        "type": "uint256",
        "internalType": "uint256"
      }
    ],
    "outputs": [
      {
        "name": "",
        "type": "uint256",
        "internalType": "uint256"
      }
    ],
    "stateMutability": "view"
  },
  {
    "type": "function",
    "name": "currentEpoch",
    "inputs": [],
    "outputs": [
      {
        "name": "",
        "type": "uint256",
        "internalType": "uint256"
      }
    ],
    "stateMutability": "view"
  },
  {
    "type": "function",
    "name": "deposit",
    "inputs": [
      {
        "name": "account",
        "type": "address",
        "internalType": "address"
      },
      {
        "name": "amount",
        "type": "uint256",
        "internalType": "uint256"
      }
    ],
    "outputs": [],
    "stateMutability": "nonpayable"
  },
  {
    "type": "function",
    "name": "draw",
    "inputs": [
      {
        "name": "epochId",
        "type": "uint256",
        "internalType": "uint256"
      },
      {
        "name": "winners",
        "type": "address[]",
        "internalType": "address[]"
      }
    ],
    "outputs": [],
    "stateMutability": "nonpayable"
  },
  {
    "type": "function",
    "name": "epochDrawn",
    "inputs": [
      {
        "name": "",
        "type": "uint256",
        "internalType": "uint256"
      }
    ],
    "outputs": [
      {
        "name": "",
        "type": "bool",
        "internalType": "bool"
      }
    ],
    "stateMutability": "view"
  },
  {
    "type": "function",
    "name": "genesisTimestamp",
    "inputs": [],
    "outputs": [
      {
        "name": "",
        "type": "uint256",
        "internalType": "uint256"
      }
    ],
    "stateMutability": "view"
  },
  {
    "type": "function",
    "name": "getCurrentEpoch",
    "inputs": [],
    "outputs": [
      {
        "name": "",
        "type": "uint256",
        "internalType": "uint256"
      }
    ],
    "stateMutability": "view"
  },
  {
    "type": "function",
    "name": "getEpochDuration",
    "inputs": [],
    "outputs": [
      {
        "name": "",
        "type": "uint256",
        "internalType": "uint256"
      }
    ],
    "stateMutability": "view"
  },
  {
    "type": "function",
    "name": "getEpochEntryDeadline",
    "inputs": [],
    "outputs": [
      {
        "name": "",
        "type": "uint256",
        "internalType": "uint256"
      }
    ],
    "stateMutability": "view"
  },
  {
    "type": "function",
    "name": "getEpochStartTime",
    "inputs": [
      {
        "name": "epochId",
        "type": "uint256",
        "internalType": "uint256"
      }
    ],
    "outputs": [
      {
        "name": "",
        "type": "uint256",
        "internalType": "uint256"
      }
    ],
    "stateMutability": "view"
  },
  {
    "type": "function",
    "name": "getFeeRecipient",
    "inputs": [],
    "outputs": [
      {
        "name": "",
        "type": "address",
        "internalType": "address"
      }
    ],
    "stateMutability": "view"
  },
  {
    "type": "function",
    "name": "getLatestEpochRemainingTime",
    "inputs": [],
    "outputs": [
      {
        "name": "",
        "type": "uint256",
        "internalType": "uint256"
      }
    ],
    "stateMutability": "view"
  },
  {
    "type": "function",
    "name": "getUserBonus",
    "inputs": [
      {
        "name": "account",
        "type": "address",
        "internalType": "address"
      }
    ],
    "outputs": [
      {
        "name": "",
        "type": "uint256",
        "internalType": "uint256"
      }
    ],
    "stateMutability": "view"
  },
  {
    "type": "function",
    "name": "getUserWeight",
    "inputs": [
      {
        "name": "account",
        "type": "address",
        "internalType": "address"
      }
    ],
    "outputs": [
      {
        "name": "",
        "type": "uint256",
        "internalType": "uint256"
      }
    ],
    "stateMutability": "view"
  },
  {
    "type": "function",
    "name": "isCurrentEpochOver",
    "inputs": [],
    "outputs": [
      {
        "name": "",
        "type": "bool",
        "internalType": "bool"
      }
    ],
    "stateMutability": "view"
  },
  {
    "type": "function",
    "name": "latestEpochStartTime",
    "inputs": [],
    "outputs": [
      {
        "name": "",
        "type": "uint256",
        "internalType": "uint256"
      }
    ],
    "stateMutability": "view"
  },
  {
    "type": "function",
    "name": "nextEpoch",
    "inputs": [],
    "outputs": [],
    "stateMutability": "nonpayable"
  },
  {
    "type": "function",
    "name": "randomGenerator",
    "inputs": [],
    "outputs": [
      {
        "name": "",
        "type": "address",
        "internalType": "contract IRandomGenerator"
      }
    ],
    "stateMutability": "view"
  },
  {
    "type": "function",
    "name": "stash",
    "inputs": [
      {
        "name": "account",
        "type": "address",
        "internalType": "address"
      },
      {
        "name": "amount",
        "type": "uint256",
        "internalType": "uint256"
      }
    ],
    "outputs": [],
    "stateMutability": "nonpayable"
  },
  {
    "type": "function",
    "name": "users",
    "inputs": [
      {
        "name": "",
        "type": "address",
        "internalType": "address"
      }
    ],
    "outputs": [
      {
        "name": "amount",
        "type": "uint256",
        "internalType": "uint256"
      },
      {
        "name": "fidelityBonus",
        "type": "uint256",
        "internalType": "uint256"
      },
      {
        "name": "lastActiveEpoch",
        "type": "uint256",
        "internalType": "uint256"
      }
    ],
    "stateMutability": "view"
  },
  {
    "type": "function",
    "name": "withdraw",
    "inputs": [
      {
        "name": "account",
        "type": "address",
        "internalType": "address"
      },
      {
        "name": "amount",
        "type": "uint256",
        "internalType": "uint256"
      }
    ],
    "outputs": [],
    "stateMutability": "nonpayable"
  },
  {
    "type": "event",
    "name": "EpochDrawn",
    "inputs": [
      {
        "name": "epochId",
        "type": "uint256",
        "indexed": false,
        "internalType": "uint256"
      },
      {
        "name": "winners",
        "type": "address[]",
        "indexed": false,
        "internalType": "address[]"
      }
    ],
    "anonymous": false
  },
  {
    "type": "event",
    "name": "NewEpochStarted",
    "inputs": [
      {
        "name": "epochId",
        "type": "uint256",
        "indexed": false,
        "internalType": "uint256"
      }
    ],
    "anonymous": false
  },
  {
    "type": "error",
    "name": "AlreadyDrawn",
    "inputs": [
      {
        "name": "epochId",
        "type": "uint256",
        "internalType": "uint256"
      }
    ]
  },
  {
    "type": "error",
    "name": "NoWinnersProvided",
    "inputs": [
      {
        "name": "epochId",
        "type": "uint256",
        "internalType": "uint256"
      }
    ]
  },
  {
    "type": "error",
    "name": "RandomNotReady",
    "inputs": [
      {
        "name": "epochId",
        "type": "uint256",
        "internalType": "uint256"
      }
    ]
  }
]
